garpix_profitbase/MANIFEST.in
garpix_profitbase/__init__.py
garpix_profitbase/apps.py
garpix_profitbase/profitbase.py
garpix_profitbase/setup.py
garpix_profitbase/__pycache__/__init__.cpython-38.pyc
garpix_profitbase/__pycache__/apps.cpython-38.pyc
garpix_profitbase/__pycache__/profitbase.cpython-38.pyc
garpix_profitbase/admin/__init__.py
garpix_profitbase/admin/config.py
garpix_profitbase/admin/__pycache__/__init__.cpython-38.pyc
garpix_profitbase/admin/__pycache__/config.cpython-38.pyc
garpix_profitbase/management/commands/profitbase_update.py
garpix_profitbase/management/commands/__pycache__/profitbase_update.cpython-38.pyc
garpix_profitbase/models/__init__.py
garpix_profitbase/models/city.py
garpix_profitbase/models/config.py
garpix_profitbase/models/empty_mixin.py
garpix_profitbase/models/house.py
garpix_profitbase/models/house_floor.py
garpix_profitbase/models/house_section.py
garpix_profitbase/models/layout_plan.py
garpix_profitbase/models/project.py
garpix_profitbase/models/property.py
garpix_profitbase/models/property_special_offer.py
garpix_profitbase/models/__pycache__/__init__.cpython-38.pyc
garpix_profitbase/models/__pycache__/city.cpython-38.pyc
garpix_profitbase/models/__pycache__/config.cpython-38.pyc
garpix_profitbase/models/__pycache__/empty_mixin.cpython-38.pyc
garpix_profitbase/models/__pycache__/house.cpython-38.pyc
garpix_profitbase/models/__pycache__/house_floor.cpython-38.pyc
garpix_profitbase/models/__pycache__/house_section.cpython-38.pyc
garpix_profitbase/models/__pycache__/layout_plan.cpython-38.pyc
garpix_profitbase/models/__pycache__/project.cpython-38.pyc
garpix_profitbase/models/__pycache__/property.cpython-38.pyc
garpix_profitbase/models/__pycache__/property_special_offer.cpython-38.pyc
garpix_profitbase-1.16.1.dist-info/METADATA
garpix_profitbase-1.16.1.dist-info/WHEEL
garpix_profitbase-1.16.1.dist-info/top_level.txt
garpix_profitbase-1.16.1.dist-info/RECORD
